ner_anonymizer/__init__.py
ner_anonymizer/ner_anonymizer.py
ner_anonymizer-0.1.6.dist-info/LICENSE
ner_anonymizer-0.1.6.dist-info/METADATA
ner_anonymizer-0.1.6.dist-info/WHEEL
ner_anonymizer-0.1.6.dist-info/top_level.txt
ner_anonymizer-0.1.6.dist-info/RECORD
