Metadata-Version: 2.1
Name: ner-anonymizer
Version: 0.1.6
Summary: Anonymizes pandas dataset and provides a hash dictionary to de-anonymize
Home-page: https://github.com/kelvnt/ner-anonymizer
Author: Kelvin Tay
Author-email: btkelvin@gmail.com
License: MIT license
Platform: UNKNOWN
Requires-Python: >=3.6.0
Requires-Dist: transformers (>=3.0.0)
Requires-Dist: torch (>=1.5.0)
Requires-Dist: torchvision (>=0.6.0)
Requires-Dist: pandas (>=1.0.0)
